keynote_highlight/__init__.py
keynote_highlight/main.py
keynote_highlight-0.0.2.dist-info/entry_points.txt
keynote_highlight-0.0.2.dist-info/WHEEL
keynote_highlight-0.0.2.dist-info/METADATA
keynote_highlight-0.0.2.dist-info/RECORD
